authorai/__init__.py
authorai/artist.py
authorai/blogger.py
authorai/core.py
authorai-0.2.2.dist-info/LICENSE
authorai-0.2.2.dist-info/METADATA
authorai-0.2.2.dist-info/WHEEL
authorai-0.2.2.dist-info/top_level.txt
authorai-0.2.2.dist-info/RECORD
