Metadata-Version: 2.1
Name: authorai
Version: 0.2.2
Summary: Enhance your creative authoring flow, leave the plumbing to AuthorAI
Home-page: https://www.authorai.org
Author: AuthorAi.org
Author-email: authorai.org@gmail.com
License: MIT
Keywords: AI generative transformer authoring automation
Classifier: Intended Audience :: Developers
Classifier: License :: OSI Approved :: MIT License
Classifier: Programming Language :: Python
Classifier: Programming Language :: Python :: 3
Classifier: Programming Language :: Python :: 3.6
Classifier: Programming Language :: Python :: 3.7
Classifier: Programming Language :: Python :: 3.8
Classifier: Programming Language :: Python :: 3.9
Classifier: Operating System :: OS Independent
License-File: LICENSE
Requires-Dist: openai
Requires-Dist: bs4
Requires-Dist: markdownify
Requires-Dist: urllib3
Requires-Dist: stability-sdk
